changelist/__init__.py
changelist/__main__.py
changelist/_cli.py
changelist/_config.py
changelist/_format.py
changelist/_objects.py
changelist/_query.py
changelist/default_config.toml
changelist-0.5.dist-info/LICENSE.txt
changelist-0.5.dist-info/METADATA
changelist-0.5.dist-info/WHEEL
changelist-0.5.dist-info/entry_points.txt
changelist-0.5.dist-info/top_level.txt
changelist-0.5.dist-info/RECORD
