Metadata-Version: 2.1
Name: changelist
Version: 0.5
License: BSD 3-Clause License
Project-URL: Source, https://github.com/scientific-python/changelist
Classifier: Development Status :: 3 - Alpha
Classifier: License :: OSI Approved :: BSD License
Classifier: Programming Language :: Python :: 3
Classifier: Programming Language :: Python :: 3.9
Classifier: Programming Language :: Python :: 3.10
Classifier: Programming Language :: Python :: 3.11
Classifier: Programming Language :: Python :: 3.12
Classifier: Programming Language :: Python :: 3 :: Only
Requires-Python: >=3.9
License-File: LICENSE.txt
Requires-Dist: requests
Requires-Dist: requests-cache
Requires-Dist: tqdm
Requires-Dist: PyGithub
Provides-Extra: lint
Requires-Dist: pre-commit ==3.6.0 ; extra == 'lint'
Provides-Extra: test
Requires-Dist: pytest ; extra == 'test'
Requires-Dist: pytest-cov ; extra == 'test'
